[{
    "id": "museums",
    "type": "circle",
    "source": {
      "type": "vector",
      "url": "mapbox://mapbox.2opop9hr"
    },
    "layout": {
      "visibility": "visible"
    },
    "paint": {
      "circle-radius": 8,
      "circle-color": "rgba(55,148,179,1)"
    },
    "sourceLayer": "museum-cusco"
  },
  {
    "id": "contours",
    "type": "line",
    "source": {
      "type": "vector",
      "url": "mapbox://mapbox.mapbox-terrain-v2"
    },
    "layout": {
      "visibility": "visible",
      "line-join": "round",
      "line-cap": "round"
    },
    "paint": {
      "line-color": "#877b59",
      "line-width": 1
    },
    "sourceLayer": "contour"
  }
]
